leveelogic/__init__.py
leveelogic/algorithms/add_berm.py
leveelogic/algorithms/add_phreatic_line.py
leveelogic/api/bro_api.py
leveelogic/api/bro_objects.py
leveelogic/api/geotop.py
leveelogic/calculations/matrix.py
leveelogic/calculations/piles.py
leveelogic/calculations/piping.py
leveelogic/calculations/settlement.py
leveelogic/external/dgeolib.py
leveelogic/external/dstabilitycalculator.py
leveelogic/external/gefxmlreader.py
leveelogic/external/internal.py
leveelogic/gis/helpers.py
leveelogic/helpers.py
leveelogic/models/datamodel.py
leveelogic/objects/__init__.py
leveelogic/objects/cpt.py
leveelogic/objects/crosssection.py
leveelogic/objects/levee.py
leveelogic/objects/referenceline.py
leveelogic/objects/soil.py
leveelogic/objects/soilcollection.py
leveelogic/objects/soillayer.py
leveelogic/objects/soilpolygon.py
leveelogic/objects/soilprofile.py
leveelogic/objects/stresses.py
leveelogic/settings.py
leveelogic/voxels/__init__.py
leveelogic/voxels/voxel_model.py
leveelogic-0.9.1.dist-info/METADATA
leveelogic-0.9.1.dist-info/WHEEL
leveelogic-0.9.1.dist-info/RECORD
