Metadata-Version: 2.3
Name: leveelogic
Version: 0.9.1
Summary: 
Author: Rob van Putten
Author-email: breinbaasnl@gmail.com
Requires-Python: >=3.10,<3.13
Classifier: Programming Language :: Python :: 3
Classifier: Programming Language :: Python :: 3.10
Classifier: Programming Language :: Python :: 3.11
Classifier: Programming Language :: Python :: 3.12
Requires-Dist: d-geolib (>=2.6.0,<3.0.0)
Requires-Dist: haversine (>=2.8.1,<3.0.0)
Requires-Dist: jinja2 (>=3.1.5,<4.0.0)
Requires-Dist: matplotlib (>=3.8.3,<4.0.0)
Requires-Dist: netcdf4 (>=1.7.2,<2.0.0)
Requires-Dist: pandas (>=2.2.2,<3.0.0)
Requires-Dist: pydantic (>=1.10.7)
Requires-Dist: pydantic-extra-types (>=2.10.2,<3.0.0)
Requires-Dist: pydantic-settings (>=2.7.1,<3.0.0)
Requires-Dist: pyproj (>=3.6.1,<4.0.0)
Requires-Dist: pyshp (>=2.3.1,<3.0.0)
Requires-Dist: pytest (>=8.2.2,<9.0.0)
Requires-Dist: python-dotenv (>=1.0.1,<2.0.0)
Requires-Dist: requests (>=2.32.3,<3.0.0)
Requires-Dist: shapely (>=2.0.6,<3.0.0)
Requires-Dist: simplejson (>=3.19.2,<4.0.0)
Requires-Dist: xmltodict (>=0.13.0,<0.14.0)
